icons/caps_off.png
icons/caps_on.png
icons/nums_off.png
icons/nums_on.png
kbm_cli/__init__.py
kbm_cli/main.py
keyboard_mate-0.1.3.dist-info/METADATA
keyboard_mate-0.1.3.dist-info/WHEEL
keyboard_mate-0.1.3.dist-info/entry_points.txt
keyboard_mate-0.1.3.dist-info/RECORD
